{
"type": "FeatureCollection",
"name": "My-House-4326",
"crs": { "type": "name", "properties": { "name": "urn:ogc:def:crs:OGC:1.3:CRS84" } },
"features": [
{ "type": "Feature", "properties": { "id": 3, "Desc.": "My House" }, "geometry": { "type": "Point", "coordinates": [ -79.051111345347309, 35.923949041674142 ] } }
]
}
